README.md
setup.py
f2db/__init__.py
f2db/f2db.py
f2db.egg-info/PKG-INFO
f2db.egg-info/SOURCES.txt
f2db.egg-info/dependency_links.txt
f2db.egg-info/top_level.txt